git_user23/__init__.py
git_user23/git_user23.py
git_user23-0.0.3.dist-info/WHEEL
git_user23-0.0.3.dist-info/METADATA
git_user23-0.0.3.dist-info/RECORD
