Metadata-Version: 2.1
Name: git-user23
Version: 0.0.3
Summary: A Python library for GitHub API integration. Retrieve user info, repositories, and more. Simplify GitHub-related tasks effortlessly.
Home-page: https://github.com/samuelogboye/git-user
License: MIT
Keywords: github,api,user,repository,git,python,library,wrapper,integration,samuelogboye
Author: Samuel Ogboye
Author-email: ogboyesam@gmail.com
Requires-Python: >=3,<4
Classifier: License :: OSI Approved :: MIT License
Classifier: Operating System :: OS Independent
Classifier: Programming Language :: Python :: 3
Classifier: Programming Language :: Python :: 3.10
Classifier: Programming Language :: Python :: 3.4
Classifier: Programming Language :: Python :: 3.5
Classifier: Programming Language :: Python :: 3.6
Classifier: Programming Language :: Python :: 3.7
Classifier: Programming Language :: Python :: 3.8
Classifier: Programming Language :: Python :: 3.9
Classifier: Programming Language :: Python :: Implementation :: CPython
Classifier: Programming Language :: Python :: Implementation :: PyPy
Project-URL: Repository, https://github.com/samuelogboye/git-user
